[
  {
    "icon": "Home",
    "name": "菜园子",
    "link": "https://www.liubaicai.net/"
  },
  {
    "icon": "Blog",
    "name": "博的客",
    "link": "https://blog.liubaicai.net/"
  },
  {
    "icon": "Image",
    "name": "遛猫网",
    "link": "http://www.6mao.wang/"
  },
  {
    "icon": "Image",
    "name": "每日必应",
    "link": "http://bing.liubaicai.net/"
  },
  {
    "icon": "Compass",
    "name": "起始页",
    "link": "https://home.liubaicai.net/"
  },
  {
    "icon": "Fire",
    "name": "今日热榜",
    "link": "https://hot.imsyy.top/"
  }
]
